termcolors/__init__.py
termcolors/base.py
termcolors/color.py
termcolors/formatter.py
termcolors/logger.py
termcolors/style.py
termcolorsfx-0.1.0.dist-info/licenses/LICENSE
termcolorsfx-0.1.0.dist-info/METADATA
termcolorsfx-0.1.0.dist-info/WHEEL
termcolorsfx-0.1.0.dist-info/top_level.txt
termcolorsfx-0.1.0.dist-info/RECORD
