Metadata-Version: 2.4
Name: termcolorsfx
Version: 0.1.0
Summary: Advanced terminal color formatting and logging
Author: Vignesh Selvaraj
Requires-Python: >=3.7
License-File: LICENSE
Dynamic: author
Dynamic: description
Dynamic: description-content-type
Dynamic: license-file
Dynamic: requires-python
Dynamic: summary
